fcollections/__init__.py
fcollections/iterable.py
fcollections/list.py
fcollections-0.1.dist-info/DESCRIPTION.rst
fcollections-0.1.dist-info/METADATA
fcollections-0.1.dist-info/metadata.json
fcollections-0.1.dist-info/RECORD
fcollections-0.1.dist-info/top_level.txt
fcollections-0.1.dist-info/WHEEL
