Metadata-Version: 2.0
Name: fcollections
Version: 0.1
Summary: functional collections for python
Home-page: https://github.com/altimin/fcollections
Author: Alexander Timin
Author-email: alexander@timin.me
License: WTFPL
Platform: UNKNOWN
